[
  {
    "_id": {
      "$oid": "663cd8bbda2083950a8b181d"
    },
    "categoryId": 1,
    "subcategoryId": 1,
    "description": "Screen (6.52\", IPS, 1600x720) / Spreadtrum SC9863A (1.6 GHz) / dual main camera: 13 MP + 2 MP, front camera: 5 MP / RAM 2 GB / 32 GB built-in memory + microSD (up to 512 GB) / 3G / LTE / GPS / support for 2 SIM cards (Nano-SIM) / Android 11 / 3200 mAh",
    "detailedDescription": [
      {
        "label": "FORGED FROM TITANIUM",
        "value": "iPhone 15 Pro has a strong and lightweight aerospace titanium body and textured frosted glass back. It is equipped with a Ceramic Shield front panel, which is stronger than the glass of any smartphone. In addition, the iPhone 15 Pro is protected against splashes, water and dust."
      }
    ],
    "price": 225,
    "quantity": 11,
    "discount": 5,
    "seller": 2,
    "brand": "ZTE",
    "state": 1,
    "rating": 1,
    "title": "ZTE Blade A51",
    "images": [
      "https://res.cloudinary.com/dw60kllwn/image/upload/v1697355087/zte_front_scqohl.webp",
      "https://rozetka-server.onrender.com/assets/telefony-tv-i-ehlektronika/phones/zte.webp",
      "https://rozetka-server.onrender.com/assets/telefony-tv-i-ehlektronika/phones/zte-3.webp",
      "https://rozetka-server.onrender.com/assets/telefony-tv-i-ehlektronika/phones/zte-4.webp"
    ],
    "country": "USA"
  },
  {
    "_id": {
      "$oid": "663cd8bbda2083950a8b1816"
    },
    "categoryId": 1,
    "subcategoryId": 2,
    "description": "Screen (6.5\", Super AMOLED, 2340x1080) / Mediatek Helio G99 (2 x 2.6 GHz + 6 x 2.0 GHz) / main triple camera: 50 MP + 5 MP + 2 MP, front camera: 13 MP / RAM 6 GB / 128 GB of built-in memory + microSD (up to 1 TB) / 3G / LTE / GPS / GLONASS / BDS / support for 2 SIM cards (Nano-SIM) / Android 13 / 5000 mAh",
    "detailedDescription": [
      {
        "label": "Samsung Galaxy A24",
        "value": "The Samsung Galaxy A24 is a powerful mid-range phone that offers a wide variety of tasks. Thanks to a powerful processor and fast RAM, this phone works well with many programs at the same time, and also provides fast launch of games and programs."
      },
      {
        "label": "Camera",
        "value": "Samsung Galaxy A24 impresses with its capabilities: the main camera allows you to take high-quality photos, and the front camera helps you take great selfies. The phone has shooting modes for portraits, night scenes, macro and more.."
      }
    ],
    "price": 650,
    "quantity": 11,
    "seller": 1,
    "brand": 6,
    "state": 1,
    "rating": 3,
    "title": "Samsung Galaxy A24",
    "images": [
      "https://res.cloudinary.com/dw60kllwn/image/upload/v1697390868/samsung_galaxy_a24_front_lzj7rg.webp",
      "https://res.cloudinary.com/dw60kllwn/image/upload/v1698255177/samsung_galaxy_a24_yrpdsh.webp",
      "https://rozetka-server.onrender.com/assets/telefony-tv-i-ehlektronika/phones/samsung_galaxy_a24-3.webp",
      "https://rozetka-server.onrender.com/assets/telefony-tv-i-ehlektronika/phones/samsung_galaxy_a24-4.webp",
      "https://rozetka-server.onrender.com/assets/telefony-tv-i-ehlektronika/phones/samsung_galaxy_a24-5.webp"
    ],
    "country": "Japan"
  },
  {
    "_id": {
      "$oid": "663cd8bbda2083950a8b1818"
    },
    "categoryId": 1,
    "subcategoryId": 2,
    "description": "Screen (6.5\", LCD, 2400x1080) / Qualcomm Snapdragon 680 (2.4 GHz) / main triple camera: 50 MP + 8 MP + 2 MP, front camera: 16 MP / RAM 8 GB / 256 GB built-in memory + microSD ( up to 1 TB) / 3G / LTE / GPS / support for 2 SIM cards (Nano-SIM) / Android 12 / 5000 mAh",
    "detailedDescription": [],
    "price": 350,
    "quantity": 11,
    "discount": 10,
    "seller": 1,
    "brand": 8,
    "state": 1,
    "rating": 3,
    "title": "Motorola G32",
    "images": [
      "https://res.cloudinary.com/dw60kllwn/image/upload/v1697355342/motorolla_front_yamsvb.webp",
      "https://rozetka-server.onrender.com/assets/telefony-tv-i-ehlektronika/phones/motorolla.webp"
    ],
    "country": "USA"
  },
  {
    "_id": {
      "$oid": "663cd8bbda2083950a8b181f"
    },
    "categoryId": 1,
    "subcategoryId": 1,
    "description": "Screen (6.56\", IPS, 1612x720) / MediaTek Helio G37 (2.3 GHz + 1.8 GHz) / dual main camera: 50 MP + AI, front camera: 8 MP / RAM 8 GB / 128 GB built-in memory + microSD ) ( up to 512 GB) / 3G / LTE / GPS / support for 2x SIM cards (Nano-SIM) / Android 13 / 5000 mAh * h",
    "detailedDescription": [],
    "price": 125,
    "quantity": 11,
    "discount": 5,
    "seller": 2,
    "brand": 9,
    "state": 1,
    "rating": 2,
    "title": "Tecno Spark 10 Pro",
    "images": [
      "https://res.cloudinary.com/dw60kllwn/image/upload/v1697355971/tecno_front_vtrdfk.webp",
      "https://rozetka-server.onrender.com/assets/telefony-tv-i-ehlektronika/phones/tecno.webp"
    ],
    "country": "Korea"
  },
  {
    "_id": {
      "$oid": "663cd8bbda2083950a8b1817"
    },
    "categoryId": 1,
    "subcategoryId": 2,
    "description": "Screen (6.1\", OLED (Super Retina XDR), 2532x1170) / Apple A15 Bionic / dual main camera: 12 MP + 12 MP, front camera: 12 MP / 128 GB of built-in memory / 3G / LTE / 5G / GPS / Nano-SIM, eSIM / iOS 15",
    "detailedDescription": [],
    "price": 350,
    "quantity": 11,
    "discount": 10,
    "seller": 1,
    "brand": 5,
    "state": 1,
    "rating": 3,
    "title": "Apple iPhone 13 128GB",
    "images": [
      "https://res.cloudinary.com/dw60kllwn/image/upload/v1697528759/221214140_11zon_xg1ptp.webp",
      "https://rozetka-server.onrender.com/assets/telefony-tv-i-ehlektronika/phones/apple_13.webp",
      "https://rozetka-server.onrender.com/assets/telefony-tv-i-ehlektronika/phones/apple_13-3.webp",
      "https://rozetka-server.onrender.com/assets/telefony-tv-i-ehlektronika/phones/apple_13-4.webp"
    ],
    "country": "China"
  },
  {
    "_id": {
      "$oid": "663cd8bbda2083950a8b181a"
    },
    "categoryId": 1,
    "subcategoryId": 2,
    "description": "Screen (6.517\", IPS, 1600x720) / Unisoc SC9863A (1.6 GHz + 1.2 GHz) / dual main camera: 13 MP + 2 MP, front 8 MP / RAM 3 GB / 64 GB internal memory + microSD (up to 256 GB ) / 3G / LTE / GPS / support for 2 SIM cards (Nano-SIM) / Android 13 / 5000 mAh * h\n",
    "detailedDescription": [],
    "price": 215,
    "quantity": 11,
    "discount": 10,
    "seller": 1,
    "brand": 10,
    "state": 1,
    "rating": 2,
    "title": "Nokia C22",
    "images": ["https://res.cloudinary.com/dw60kllwn/image/upload/v1697304946/nokia_c22_m3uerw.webp"],
    "country": "China"
  },
  {
    "_id": {
      "$oid": "663cd8bbda2083950a8b181b"
    },
    "categoryId": 1,
    "subcategoryId": 1,
    "description": "MediaTek Helio G36 processor, stunning dual 8 MP camera with artificial intelligence, large 6.52'' display with HD+ resolution, 5000 mAh battery – all this about Xiaomi Redmi A2.",
    "detailedDescription": [],
    "price": 405,
    "quantity": 11,
    "discount": 30,
    "seller": 1,
    "brand": 11,
    "state": 1,
    "rating": 5,
    "title": "Xiaomi Redmi",
    "images": ["https://rozetka-server.onrender.com/assets/telefony-tv-i-ehlektronika/phones/xiaomi_redmi.webp"],
    "country": "China"
  },
  {
    "_id": {
      "$oid": "663cd8bbda2083950a8b1820"
    },
    "categoryId": 1,
    "subcategoryId": 1,
    "description": "Screen (6.55\", P-OLED, 2400x1080) / MediaTek Dimensity 7030 (2.5 GHz + 2.0 GHz) / dual main camera: 50 MP + 13 MP, front camera: 32 MP / RAM 12 GB / 256 GB built-in memory / 3G / LTE / 5G / GPS / Nano-SIM + eSIM / Android 13 / 5000 mAh.",
    "detailedDescription": [],
    "price": 265,
    "quantity": 11,
    "discount": 10,
    "seller": 1,
    "brand": 8,
    "state": 1,
    "rating": 4,
    "title": "Мобільний телефон Motorola Edge 30 Neo",
    "images": [
      "https://res.cloudinary.com/dw60kllwn/image/upload/v1697355250/motorola_30_front_uutbmx.webp",
      "https://rozetka-server.onrender.com/assets/telefony-tv-i-ehlektronika/phones/motorola_30.webp",
      "https://rozetka-server.onrender.com/assets/telefony-tv-i-ehlektronika/phones/motorola_30-3.webp",
      "https://rozetka-server.onrender.com/assets/telefony-tv-i-ehlektronika/phones/motorola_30-4.webp",
      "https://rozetka-server.onrender.com/assets/telefony-tv-i-ehlektronika/phones/motorola_30-5.webp"
    ],
    "country": "China"
  },
  {
    "_id": {
      "$oid": "663cd8bbda2083950a8b1819"
    },
    "categoryId": 1,
    "subcategoryId": 2,
    "description": "Screen (6.1\", OLED (Super Retina XDR), 2556x1179) / Apple A17 Pro / main triple camera: 48 MP + 12 MP + 12 MP, front camera: 12 MP / 256 GB of built-in memory / 3G / LTE / 5G / GPS / Nano-SIM / iOS 17",
    "detailedDescription": [],
    "price": 1115,
    "quantity": 11,
    "discount": 10,
    "seller": 1,
    "brand": 5,
    "state": 1,
    "rating": 3,
    "title": "Apple iPhone 14 Pro",
    "images": [
      "https://rozetka-server.onrender.com/assets/telefony-tv-i-ehlektronika/phones/apple_14_front.webp",
      "https://rozetka-server.onrender.com/assets/telefony-tv-i-ehlektronika/phones/apple_14.webp"
    ],
    "country": "Japan"
  },
  {
    "_id": {
      "$oid": "663cd8bbda2083950a8b181c"
    },
    "categoryId": 1,
    "subcategoryId": 1,
    "description": "This is an example product description.",
    "detailedDescription": [],
    "price": 225,
    "quantity": 11,
    "discount": 5,
    "seller": 2,
    "brand": 12,
    "state": 1,
    "rating": 5,
    "title": "Мобільний телефон Poco M4 Pro 6",
    "images": [
      "https://res.cloudinary.com/dw60kllwn/image/upload/v1697355199/poco_front_tbcydv.webp",
      "https://rozetka-server.onrender.com/assets/telefony-tv-i-ehlektronika/phones/poco.webp"
    ],
    "country": "Belgium"
  },
  {
    "_id": {
      "$oid": "663cd8bbda2083950a8b181e"
    },
    "categoryId": 1,
    "subcategoryId": 1,
    "description": "This is an example product description.",
    "detailedDescription": [],
    "price": 225,
    "quantity": 11,
    "discount": 5,
    "seller": 2,
    "brand": 11,
    "state": 1,
    "rating": 2,
    "title": "Мобільний телефон Xiaomi 12 Lite 6",
    "images": [
      "https://rozetka-server.onrender.com/assets/telefony-tv-i-ehlektronika/phones/xiaomi_12_front.webp",
      "https://rozetka-server.onrender.com/assets/telefony-tv-i-ehlektronika/phones/xiaomi_12.webp"
    ],
    "country": "China"
  },
  {
    "_id": {
      "$oid": "663db003da2083950a8b1824"
    },
    "categoryId": 3,
    "subcategoryId": 1,
    "description": "This is an example product description.",
    "detailedDescription": [],
    "price": 945,
    "quantity": 11,
    "discount": 20,
    "seller": 1,
    "brand": 13,
    "state": 1,
    "rating": 3,
    "title": "Двокамерний холодильник BEKO",
    "images": [
      "https://res.cloudinary.com/dw60kllwn/image/upload/v1702037614/beko_front_ljzcoz.webp",
      "https://evergreen-purrfect-agenda.glitch.me/assets/household-appliances/large_household_appliances/beko.webp"
    ],
    "country": "Korea"
  },
  {
    "_id": {
      "$oid": "663db003da2083950a8b1823"
    },
    "categoryId": 3,
    "subcategoryId": 1,
    "description": "This is an example product description.",
    "detailedDescription": [],
    "price": 650,
    "quantity": 11,
    "discount": 10,
    "seller": 1,
    "brand": 14,
    "state": 1,
    "rating": 5,
    "title": "Плита комбінована GORENJE GK5C40WF",
    "images": [
      "https://res.cloudinary.com/dw60kllwn/image/upload/v1702037583/gorenje_front_rla25h.webp",
      "https://evergreen-purrfect-agenda.glitch.me/assets/household-appliances/large_household_appliances/gorenje.webp"
    ],
    "country": "China"
  },
  {
    "_id": {
      "$oid": "663db05cda2083950a8b1826"
    },
    "categoryId": 3,
    "subcategoryId": 1,
    "description": "This is an example product description.",
    "detailedDescription": [],
    "price": 999,
    "quantity": 11,
    "discount": 10,
    "seller": 1,
    "brand": 15,
    "state": 1,
    "rating": 4,
    "title": "Холодильник INDESIT LI6 S1E W",
    "images": [
      "https://res.cloudinary.com/dw60kllwn/image/upload/v1702037644/indesit_front_v0ep1a.webp",
      "https://evergreen-purrfect-agenda.glitch.me/assets/household-appliances/large_household_appliances/indesit.webp"
    ],
    "country": "China"
  },
  {
    "_id": {
      "$oid": "663db108da2083950a8b1827"
    },
    "categoryId": 4,
    "subcategoryId": 1,
    "description": "This is an example product description.",
    "detailedDescription": [],
    "price": 799,
    "quantity": 11,
    "discount": 10,
    "seller": 1,
    "brand": 16,
    "state": 1,
    "rating": 3,
    "title": "Велосипед CORRADO Piemont DB",
    "images": ["https://res.cloudinary.com/dw60kllwn/image/upload/v1700999791/144339014_tyi7if.webp"],
    "country": "China"
  },
  {
    "_id": {
      "$oid": "663db108da2083950a8b1829"
    },
    "categoryId": 4,
    "subcategoryId": 1,
    "description": "This is an example product description.",
    "detailedDescription": [],
    "price": 350,
    "quantity": 11,
    "seller": 1,
    "brand": 17,
    "state": 1,
    "rating": 2,
    "title": "Котушка карпова Brain Apex Double Reel Baitrunner",
    "images": ["https://res.cloudinary.com/dw60kllwn/image/upload/v1700924020/88232645_zz5cpl.webp"],
    "country": "China"
  },
  {
    "_id": {
      "$oid": "663db108da2083950a8b1828"
    },
    "categoryId": 4,
    "subcategoryId": 1,
    "description": "This is an example product description.",
    "detailedDescription": [],
    "price": 599,
    "quantity": 11,
    "seller": 1,
    "brand": 18,
    "state": 1,
    "rating": 3,
    "title": "Bike Formula MOTION AM",
    "images": ["https://res.cloudinary.com/dw60kllwn/image/upload/v1701002399/315835458_moinei.jpg"],
    "country": "UK"
  }
]
